CONTRIBUTING.md
MANIFEST.in
README.rst
setup.py
docs/HISTORY.txt
docs/LICENSE.GPL
docs/LICENSE.txt
eea/__init__.py
eea.progress.editing.egg-info/PKG-INFO
eea.progress.editing.egg-info/SOURCES.txt
eea.progress.editing.egg-info/dependency_links.txt
eea.progress.editing.egg-info/entry_points.txt
eea.progress.editing.egg-info/namespace_packages.txt
eea.progress.editing.egg-info/not-zip-safe
eea.progress.editing.egg-info/requires.txt
eea.progress.editing.egg-info/top_level.txt
eea/progress/__init__.py
eea/progress/editing/README.txt
eea/progress/editing/__init__.py
eea/progress/editing/config.py
eea/progress/editing/configure.zcml
eea/progress/editing/interfaces.py
eea/progress/editing/profiles.zcml
eea/progress/editing/setuphandlers.py
eea/progress/editing/version.txt
eea/progress/editing/api/__init__.py
eea/progress/editing/api/adapters.py
eea/progress/editing/api/configure.zcml
eea/progress/editing/browser/__init__.py
eea/progress/editing/browser/configure.zcml
eea/progress/editing/browser/controlpanel.py
eea/progress/editing/browser/view.py
eea/progress/editing/locales/__init__.py
eea/progress/editing/locales/eea.pot
eea/progress/editing/locales/plone-manual.pot
eea/progress/editing/locales/update.sh
eea/progress/editing/locales/bg/LC_MESSAGES/eea.po
eea/progress/editing/locales/bg/LC_MESSAGES/plone.po
eea/progress/editing/locales/cs/LC_MESSAGES/eea.po
eea/progress/editing/locales/cs/LC_MESSAGES/plone.po
eea/progress/editing/locales/da/LC_MESSAGES/eea.po
eea/progress/editing/locales/da/LC_MESSAGES/plone.po
eea/progress/editing/locales/de/LC_MESSAGES/eea.po
eea/progress/editing/locales/de/LC_MESSAGES/plone.po
eea/progress/editing/locales/el/LC_MESSAGES/eea.po
eea/progress/editing/locales/el/LC_MESSAGES/plone.po
eea/progress/editing/locales/en/LC_MESSAGES/eea.po
eea/progress/editing/locales/en/LC_MESSAGES/plone.po
eea/progress/editing/locales/es/LC_MESSAGES/eea.po
eea/progress/editing/locales/es/LC_MESSAGES/plone.po
eea/progress/editing/locales/et/LC_MESSAGES/eea.po
eea/progress/editing/locales/et/LC_MESSAGES/plone.po
eea/progress/editing/locales/eu/LC_MESSAGES/eea.po
eea/progress/editing/locales/eu/LC_MESSAGES/plone.po
eea/progress/editing/locales/fi/LC_MESSAGES/eea.po
eea/progress/editing/locales/fi/LC_MESSAGES/plone.po
eea/progress/editing/locales/fr/LC_MESSAGES/eea.po
